nada_dataprofilering/__init__.py
nada_dataprofilering/connectors/__init__.py
nada_dataprofilering/connectors/oracle.py
nada_dataprofilering/exceptions/__init__.py
nada_dataprofilering/exceptions/vizualisation_exceptions.py
nada_dataprofilering/sql_script_generator/__init__.py
nada_dataprofilering/sql_script_generator/date_metrics.py
nada_dataprofilering/sql_script_generator/numeric_metrics.py
nada_dataprofilering/sql_script_generator/standard_metrics.py
nada_dataprofilering/sql_script_generator/util_sql_scripts.py
nada_dataprofilering/sql_script_generator/varchar2_metrics.py
nada_dataprofilering/utils/__init__.py
nada_dataprofilering/utils/secrets_importer.py
nada_dataprofilering/vizualisation/__init__.py
nada_dataprofilering/vizualisation/bins.py
nada_dataprofilering/vizualisation/histogram.py
nada_dataprofilering/vizualisation/table_data.py
nada_dataprofilering-1.0.13.dist-info/METADATA
nada_dataprofilering-1.0.13.dist-info/WHEEL
nada_dataprofilering-1.0.13.dist-info/top_level.txt
nada_dataprofilering-1.0.13.dist-info/RECORD
